pysvd/__init__.py
pysvd/classes.py
pysvd/element.py
pysvd/node.py
pysvd/parser.py
pysvd/type.py
pysvd/version.py
scripts/__init__.py
scripts/gpio_generator.py
scripts/svd2register.py
scripts/svd2rst.py
scripts/svd_duplicates.py
test/__init__.py
test/test_classes.py
test/test_elements.py
test/test_node.py
test/test_parser.py
test/test_special.py
test/test_tree.py
test/test_type.py
pysvd-0.2.3.dist-info/LICENSE
pysvd-0.2.3.dist-info/METADATA
pysvd-0.2.3.dist-info/WHEEL
pysvd-0.2.3.dist-info/entry_points.txt
pysvd-0.2.3.dist-info/top_level.txt
pysvd-0.2.3.dist-info/RECORD
