Metadata-Version: 2.1
Name: pysvd
Version: 0.2.3
Summary: System View Description parser
Home-page: https://code.fueldner.net/opensource/pysvd
Author: Benjamin Füldner
Author-email: benjamin@fueldner.net
License: MIT
Project-URL: Bug Reports, https://github.com/bfueldner/pysvd/issues
Project-URL: Source, https://github.com/bfueldner/pysvd
Keywords: SVD CMSIS ARM
Platform: UNKNOWN
Classifier: Development Status :: 3 - Alpha
Classifier: Intended Audience :: Developers
Classifier: License :: OSI Approved :: MIT License
Classifier: Operating System :: OS Independent
Classifier: Programming Language :: Python :: 3
Classifier: Programming Language :: Python :: 3.5
Classifier: Programming Language :: Python :: 3.6
Classifier: Programming Language :: Python :: 3.7
Classifier: Topic :: System :: Hardware
Classifier: Topic :: System :: Hardware :: Hardware Drivers
Classifier: Topic :: Software Development :: Code Generators
Classifier: Topic :: Software Development :: Embedded Systems
Requires-Python: >=3.5
